uselesspackage/__init__.py
uselesspackage/demo.py
uselesspackage-0.0.3.dist-info/LICENSE
uselesspackage-0.0.3.dist-info/METADATA
uselesspackage-0.0.3.dist-info/WHEEL
uselesspackage-0.0.3.dist-info/top_level.txt
uselesspackage-0.0.3.dist-info/RECORD
