Metadata-Version: 2.1
Name: uselesspackage
Version: 0.0.3
Summary: Useless package for demo purposes
Home-page: UNKNOWN
Author: Nikolai Limbrunner
Author-email: nikolai.limbrunner@gmail.com
License: UNKNOWN
Platform: UNKNOWN
Requires-Python: >=3.6
License-File: LICENSE
